lsaBGC/__init__.py
lsaBGC/processing.py
lsaBGC/util.py
lsaBGC-1.36.data/scripts/GSeeF.py
lsaBGC-1.36.data/scripts/compareBGCtoGenomeCodonUsage.py
lsaBGC-1.36.data/scripts/createPickleOfSampleAnnotationListingFile.py
lsaBGC-1.36.data/scripts/listAllBGCGenbanksInDirectory.py
lsaBGC-1.36.data/scripts/listAllGenomesInDirectory.py
lsaBGC-1.36.data/scripts/lsaBGC-AutoAnalyze.py
lsaBGC-1.36.data/scripts/lsaBGC-AutoExpansion.py
lsaBGC-1.36.data/scripts/lsaBGC-Cluster.py
lsaBGC-1.36.data/scripts/lsaBGC-ComprehenSeeIve.py
lsaBGC-1.36.data/scripts/lsaBGC-DiscoVary.py
lsaBGC-1.36.data/scripts/lsaBGC-Divergence.py
lsaBGC-1.36.data/scripts/lsaBGC-Easy.py
lsaBGC-1.36.data/scripts/lsaBGC-Euk-Easy.py
lsaBGC-1.36.data/scripts/lsaBGC-Expansion.py
lsaBGC-1.36.data/scripts/lsaBGC-MIBiGMapper.py
lsaBGC-1.36.data/scripts/lsaBGC-PopGene.py
lsaBGC-1.36.data/scripts/lsaBGC-Ready.py
lsaBGC-1.36.data/scripts/lsaBGC-Refiner.py
lsaBGC-1.36.data/scripts/lsaBGC-See.py
lsaBGC-1.36.data/scripts/popSizeAndSampleSelector.py
lsaBGC-1.36.data/scripts/processAndReformatNCBIGenbanks.py
lsaBGC-1.36.data/scripts/readifyAdditionalGenomes.py
lsaBGC-1.36.data/scripts/runProdigalAndMakeProperGenbank.py
lsaBGC-1.36.data/scripts/setup_annotation_dbs.py
lsaBGC-1.36.data/scripts/setup_bigscape.py
lsaBGC-1.36.data/scripts/simpleProteinExtraction.py
lsaBGC-1.36.data/scripts/visualize_BGC-Ome.py
lsaBGC-1.36.dist-info/LICENSE
lsaBGC-1.36.dist-info/METADATA
lsaBGC-1.36.dist-info/WHEEL
lsaBGC-1.36.dist-info/top_level.txt
lsaBGC-1.36.dist-info/RECORD
