Metadata-Version: 2.1
Name: lsaBGC
Version: 1.36
Summary: Suite for comparative genomic, population genetics and evolutionary analysis, as well as metagenomic mining of micro-evolutionary novelty in BGCs all in the context of a single lineage of interest.
Home-page: http://github.com/Kalan-Lab/lsaBGC/
Author: Rauf Salamzade
Author-email: salamzader@gmail.com
License: BSD-3
License-File: LICENSE
